nightmares/__init__.py
nightmares/cli.py
nightmares/modules/__init__.py
nightmares/modules/commands.py
nightmares/scripts/__init__.py
nightmares/scripts/evil_syntax.py
nightmares/scripts/hello_world.py
nightmares/scripts/infinite_loop.py
nightmares/scripts/loader.py
nightmares/scripts/random_error.py
nightmares/scripts/spaghetti_code.py
nightmares/scripts/troll_function.py
nightmares/utils/__init__.py
nightmares/utils/easter_eggs.py
pynightmares-0.1.0.dist-info/METADATA
pynightmares-0.1.0.dist-info/WHEEL
pynightmares-0.1.0.dist-info/entry_points.txt
pynightmares-0.1.0.dist-info/top_level.txt
pynightmares-0.1.0.dist-info/RECORD
